{
  "project_info": {
    "project_number": "103060110436",
    "firebase_url": "https://pianoapp-3c3a2-default-rtdb.firebaseio.com/",

    "project_id": "pianoapp-3c3a2",
    "storage_bucket": "pianoapp-3c3a2.appspot.com"
  },
  "client": [
    {
      "client_info": {
        "mobilesdk_app_id": "1:103060110436:android:1976251c09efc02a79b371",
        "android_client_info": {
          "package_name": "pl.mlynarczyk.pianoapp"
        }
      },
      "oauth_client": [],
      "api_key": [
        {
          "current_key": "AIzaSyC-mWGotLjeqn9XE6-oQ8m9WrzfOX5dwww"
        }
      ],
      "services": {
        "appinvite_service": {
          "other_platform_oauth_client": []
        }
      }
    }
  ],
  "configuration_version": "2"
}